CardRL/__init__.py
CardRL-0.0.2.dist-info/METADATA
CardRL-0.0.2.dist-info/RECORD
CardRL-0.0.2.dist-info/WHEEL
CardRL-0.0.2.dist-info/top_level.txt
