Metadata-Version: 2.1
Name: CardRL
Version: 0.0.2
Summary: A Python Card Game Environment
Home-page: https://github.com/vrishank97/CardRL
Author: Vrishank Bhardwaj, Kartik Gupta
Author-email: vrishank1997@gmail.com
License: UNKNOWN
Platform: UNKNOWN
Classifier: Programming Language :: Python :: 3
Classifier: License :: OSI Approved :: MIT License
Classifier: Operating System :: OS Independent
